hex_robo_utils/__init__.py
hex_robo_utils/ctrl_util.py
hex_robo_utils/dyn_util.py
hex_robo_utils/hdf5_reader.py
hex_robo_utils/hdf5_writer.py
hex_robo_utils/math_utils.py
hex_robo_utils/obs_util.py
hex_robo_utils/plan_util.py
hex_robo_utils/plot_util.py
hex_robo_utils-0.2.11.dist-info/licenses/LICENSE
hex_robo_utils-0.2.11.dist-info/METADATA
hex_robo_utils-0.2.11.dist-info/WHEEL
hex_robo_utils-0.2.11.dist-info/top_level.txt
hex_robo_utils-0.2.11.dist-info/RECORD
