Metadata-Version: 2.4
Name: hex_robo_utils
Version: 0.2.11
Summary: HEXFELLOW Robotics Utilities
Author-email: Dong Zhaorui <joray.dong@hexfellow.com>
Maintainer-email: jecjune <zejun.chen@hexfellow.com>, Dong Zhaorui <joray.dong@hexfellow.com>
License-Expression: Apache-2.0
Project-URL: Homepage, https://github.com/hexfellow/hex_robo_utils
Project-URL: Repository, https://github.com/hexfellow/hex_robo_utils.git
Project-URL: Bug Tracker, https://github.com/hexfellow/hex_robo_utils/issues
Project-URL: Documentation, https://github.com/hexfellow/hex_robo_utils/wiki
Keywords: hex_robo_utils
Classifier: Development Status :: 4 - Beta
Classifier: Intended Audience :: Developers
Classifier: Intended Audience :: Science/Research
Classifier: Topic :: Software Development :: Libraries :: Python Modules
Classifier: Programming Language :: Python :: 3
Classifier: Programming Language :: Python :: 3.10
Classifier: Programming Language :: Python :: 3.11
Classifier: Programming Language :: Python :: 3.12
Classifier: Operating System :: POSIX :: Linux
Requires-Python: >=3.8
License-File: LICENSE
Requires-Dist: numpy>=2.2.6
Requires-Dist: hex_dynamic>=0.1.3
Provides-Extra: hdf5
Requires-Dist: h5py>=3.14.0; extra == "hdf5"
Provides-Extra: all
Requires-Dist: h5py>=3.14.0; extra == "all"
Dynamic: license-file
